robot_list/__init__.py
robot_list/robot_list.py
robot_list-0.0.8.dist-info/LICENSE
robot_list-0.0.8.dist-info/METADATA
robot_list-0.0.8.dist-info/WHEEL
robot_list-0.0.8.dist-info/top_level.txt
robot_list-0.0.8.dist-info/RECORD
