Metadata-Version: 2.1
Name: robot_list
Version: 0.0.8
Summary: This is a package which lists the robot framework tests using robot command line arguments
Home-page: https://github.com/Venixa/robot_list
Author: Venixa Innovations
Author-email: venixainnovations@gmail.com
Project-URL: Bug Tracker, https://github.com/Venixa/robot_list/issues
Keywords: robot framework list,list robotframework tests,list robot
Classifier: Programming Language :: Python :: 3
Classifier: License :: OSI Approved :: MIT License
Classifier: Operating System :: OS Independent
Requires-Python: >=3.6
License-File: LICENSE
Requires-Dist: xmltodict ==0.13.0
